truthsys-0.1.1.dist-info/METADATA
truthsys-0.1.1.dist-info/WHEEL
truthsys-0.1.1.dist-info/entry_points.txt
truthsys/__init__.py
truthsys/_version.py
truthsys/client.py
truthsys/errors.py
truthsys/influence.py
truthsys/parse_response.py
truthsys/ruling.py
truthsys/schemas/__init__.py
truthsys/schemas/common.py
truthsys/schemas/enums.py
truthsys/schemas/inputs.py
truthsys/schemas/outputs.py
truthsys/source.py
truthsys/statement.py
truthsys/verdict.py
truthsys-0.1.1.dist-info/RECORD
