Metadata-Version: 2.1
Name: truthsys
Version: 0.1.1
Summary: SDK for truthsystems.ai, a hallucination detection API
Author-Email: Truth Systems <alex@truthsystems.ai>
License: Proprietary
Classifier: Development Status :: 4 - Beta
Classifier: Intended Audience :: Developers
Classifier: License :: Other/Proprietary License
Classifier: Programming Language :: Python :: 3
Classifier: Programming Language :: Python :: 3.10
Classifier: Programming Language :: Python :: 3.11
Classifier: Programming Language :: Python :: 3.12
Classifier: Programming Language :: Python :: 3.13
Classifier: Topic :: Software Development :: Libraries :: Python Modules
Classifier: Topic :: Scientific/Engineering :: Artificial Intelligence
Classifier: Typing :: Typed
Project-URL: Homepage, https://truthsystems.ai
Requires-Python: >=3.10
Requires-Dist: pydantic<3.0.0,>=2.0.0
Requires-Dist: httpx<0.29.0,>=0.25.0
